hmmer-3.4.0.2.dist-info/RECORD
hmmer-3.4.0.2.dist-info/LICENSE
hmmer-3.4.0.2.dist-info/WHEEL
hmmer-3.4.0.2.dist-info/entry_points.txt
hmmer-3.4.0.2.dist-info/METADATA
hmmer/__init__.py
hmmer/data/bin/hmmalign
hmmer/data/bin/hmmconvert
hmmer/data/bin/hmmfetch
hmmer/data/bin/hmmstat
hmmer/data/bin/hmmlogo
hmmer/data/bin/hmmpgmd
hmmer/data/bin/hmmsim
hmmer/data/bin/hmmbuild
hmmer/data/bin/hmmemit
hmmer/data/bin/hmmerfm-exactmatch
hmmer/data/bin/hmmpgmd_shard
hmmer/data/bin/nhmmer
hmmer/data/bin/hmmc2
hmmer/data/bin/nhmmscan
hmmer/data/bin/alimask
hmmer/data/bin/hmmpress
hmmer/data/bin/makehmmerdb
hmmer/data/bin/hmmscan
hmmer/data/bin/jackhmmer
hmmer/data/bin/phmmer
hmmer/data/bin/hmmsearch
