Metadata-Version: 2.1
Name: hmmer
Version: 3.4.0.2
Summary: HMMER binaries.
License: MIT
Author: Danilo Horta
Author-email: horta@ebi.ac.uk
Requires-Python: >=3.9,<4.0
Classifier: License :: OSI Approved :: MIT License
Classifier: Programming Language :: Python :: 3
Classifier: Programming Language :: Python :: 3.9
Classifier: Programming Language :: Python :: 3.10
Classifier: Programming Language :: Python :: 3.11
Classifier: Programming Language :: Python :: 3.12
Classifier: Programming Language :: Python :: 3.13
